ZimPhoneValidate/__init__.py
ZimPhoneValidate/validate.py
ZimPhoneValidate/Examples/example.py
ZimPhoneValidate-1.1.5.dist-info/LICENSE
ZimPhoneValidate-1.1.5.dist-info/METADATA
ZimPhoneValidate-1.1.5.dist-info/WHEEL
ZimPhoneValidate-1.1.5.dist-info/entry_points.txt
ZimPhoneValidate-1.1.5.dist-info/top_level.txt
ZimPhoneValidate-1.1.5.dist-info/RECORD
